num_radix/__init__.py
num_radix/__main__.py
num_radix-1.0.2.dist-info/METADATA
num_radix-1.0.2.dist-info/RECORD
num_radix-1.0.2.dist-info/WHEEL
num_radix-1.0.2.dist-info/entry_points.txt
num_radix-1.0.2.dist-info/top_level.txt
