Metadata-Version: 2.1
Name: num-radix
Version: 1.0.2
Summary: Number radix/base encoding, decoding and formatting
Home-page: https://github.com/2sh/num-radix
Author: Seán Hewitt
Author-email: contact@2sh.me
License: UNKNOWN
Platform: UNKNOWN
Classifier: Programming Language :: Python :: 3
Classifier: License :: OSI Approved :: GNU General Public License v3 or later (GPLv3+)
Classifier: Operating System :: OS Independent
Classifier: Topic :: Scientific/Engineering :: Mathematics
Requires-Python: >=3
